NielsenDSRS/__init__.py
NielsenDSRS/module.py
NielsenIQRetail-0.2.4.dist-info/LICENSE
NielsenIQRetail-0.2.4.dist-info/METADATA
NielsenIQRetail-0.2.4.dist-info/WHEEL
NielsenIQRetail-0.2.4.dist-info/top_level.txt
NielsenIQRetail-0.2.4.dist-info/RECORD
