Metadata-Version: 2.1
Name: NielsenIQRetail
Version: 0.2.4
Summary: NielsenIQ Reader’s main purpose is to facilitate ease of processing of NielsenIQ Retail Scanner data
Home-page: https://github.com/pratikrelekar/NielsenDSRS
Author: Pratik Relekar, Hrishikesh Relekar, Matias Carrasco Kind
Author-email: relekar2@illinois.edu, hrishkesh.relekar@chicagobooth.edu, mcarras2@illinois.edu
Classifier: Programming Language :: Python :: 3
Classifier: License :: OSI Approved :: MIT License
Classifier: Operating System :: OS Independent
Requires-Python: >=3.6
License-File: LICENSE
Requires-Dist: dask[dataframe] ==2024.1.1
Requires-Dist: distributed ==2024.1.1
Requires-Dist: numpy ==1.26.3
Requires-Dist: pandas ==2.2.0
Requires-Dist: toolz ==0.12.0
